mend/__init__.py
mend/cli/__init__.py
mend/cli/generators.py
mend/cli/main.py
mend/cli/plugins.py
mend/files/__init__.py
mend/files/blob.py
mend/files/tree.py
mend/generators/__init__.py
mend/generators/file.py
mend/generators/template.py
mend/plugins/__init__.py
mend/plugins/copy.py
mend/plugins/diff.py
mend/plugins/github.py
mend/protocols/__init__.py
mend/protocols/blob.py
mend/protocols/generator.py
mend/protocols/parameters.py
mend/protocols/plugin.py
mend/protocols/tree.py
mend/templates/__init__.py
mend/templates/blob.py
mend/templates/tree.py
mend-0.6.0.dist-info/LICENSE
mend-0.6.0.dist-info/METADATA
mend-0.6.0.dist-info/WHEEL
mend-0.6.0.dist-info/entry_points.txt
mend-0.6.0.dist-info/top_level.txt
mend-0.6.0.dist-info/RECORD
